apiverve_spamdetector/__init__.py
apiverve_spamdetector/apiClient.py
apiverve_spamdetector/exceptions.py
apiverve_spamdetector/setup.py
apiverve_spamdetector/setup_dep.py
apiverve_spamdetector/tests/__init__.py
apiverve_spamdetector/tests/test_api.py
apiverve_spamdetector-1.1.5.dist-info/LICENSE
apiverve_spamdetector-1.1.5.dist-info/METADATA
apiverve_spamdetector-1.1.5.dist-info/WHEEL
apiverve_spamdetector-1.1.5.dist-info/top_level.txt
apiverve_spamdetector-1.1.5.dist-info/RECORD
